af_opt/__init__.py
af_opt/model.py
af_opt/problem.py
af_opt/recorders.py
af_opt/util.py
af_opt/version.py
af_opt/components/__init__.py
af_opt/components/airfoil.py
af_opt/components/geometry.py
af_opt/components/xfoil.py
Airfoil_Optimizer-0.9.0.dist-info/LICENSE
Airfoil_Optimizer-0.9.0.dist-info/METADATA
Airfoil_Optimizer-0.9.0.dist-info/WHEEL
Airfoil_Optimizer-0.9.0.dist-info/top_level.txt
Airfoil_Optimizer-0.9.0.dist-info/RECORD
